codigodamata-0.0.19-nspkg.pth
docassemble/codigodamata/__init__.py
docassemble/codigodamata/demodb.py
docassemble/codigodamata/google_sheets.py
docassemble/codigodamata/data/questions/ambiental_01_pagina_inicial.yml
docassemble/codigodamata/data/questions/ambiental_civil_descricao_ilicito_ambiental.yml
docassemble/codigodamata/data/questions/ambiental_civil_inicio.yml
docassemble/codigodamata/data/questions/ambiental_civil_teses.yml
docassemble/codigodamata/data/questions/ambiental_geral_composicao_civil_dano_ambiental.yml
docassemble/codigodamata/data/questions/ambiental_geral_composicao_civil_dano_ambiental_var.yml
docassemble/codigodamata/data/questions/ambiental_geral_descricao_fato_ilicito.yml
docassemble/codigodamata/data/questions/ambiental_penal_analise_institutos_despenalizadores.yml
docassemble/codigodamata/data/questions/ambiental_penal_escolha_crime.yml
docassemble/codigodamata/data/questions/ambiental_penal_inicio.yml
docassemble/codigodamata/data/questions/ambiental_penal_proposta_PRD.yml
docassemble/codigodamata/data/questions/ambiental_penal_teses.yml
docassemble/codigodamata/data/questions/ambiental_representacao_cidada_descricao_fato.yml
docassemble/codigodamata/data/questions/ambiental_representacao_cidada_inicio.yml
docassemble/codigodamata/data/questions/ambiental_valoracao_dano_md.yml
docassemble/codigodamata/data/questions/ambiental_valoracao_dano_pjedaou.yml
docassemble/codigodamata/data/questions/comum_base_dados_cadastrais.yml
docassemble/codigodamata/data/questions/comum_confirmar_competencia.yml
docassemble/codigodamata/data/questions/comum_dados_orgao.yml
docassemble/codigodamata/data/questions/comum_dados_proc.yml
docassemble/codigodamata/data/questions/comum_qualificacao_partes.yml
docassemble/codigodamata/data/questions/dev_denuncia_md.yml
docassemble/codigodamata/data/questions/sqlobject_teste.yml
docassemble/codigodamata/data/questions/test.yml
docassemble/codigodamata/data/questions/teste Introduction to Markdown.yml
codigodamata-0.0.19.dist-info/LICENSE
codigodamata-0.0.19.dist-info/METADATA
codigodamata-0.0.19.dist-info/WHEEL
codigodamata-0.0.19.dist-info/namespace_packages.txt
codigodamata-0.0.19.dist-info/top_level.txt
codigodamata-0.0.19.dist-info/RECORD
