Metadata-Version: 2.1
Name: codigodamata
Version: 0.0.19
Summary: A docassemble package for enviromental crimes
Home-page: https://codigodamata.consciencia.eco.br/
Author: Cláudio Ângelo Correa Gonzaga,Roberto Vasconcelos Novaes
Author-email: claudioacgonzaga@gmail.com,rnovaes@ufmg.br
License: The MIT License (MIT)
Platform: UNKNOWN
Requires-Dist: zipp
